admin_enhancer/models.py
admin_enhancer/admin.py
admin_enhancer/__init__.py
admin_enhancer/widgets.py
admin_enhancer/static/admin_enhancer/js/related-widget-wrapper.js
admin_enhancer/static/admin_enhancer/css/related-widget-wrapper.css
admin_enhancer/templates/admin_enhancer/dismiss-change-related-popup.html
admin_enhancer/templates/admin_enhancer/dismiss-delete-related-popup.html
admin_enhancer/templates/admin_enhancer/related-widget-wrapper.html
admin_enhancer/locale/fr/LC_MESSAGES/django.mo
admin_enhancer/locale/fr/LC_MESSAGES/django.po
admin_enhancer/contrib/__init__.py
admin_enhancer/contrib/filer/admin.py
admin_enhancer/contrib/filer/__init__.py
admin_enhancer/contrib/djangocms/admin.py
admin_enhancer/contrib/djangocms/__init__.py
django_admin_enhancer-1.0.0.dist-info/WHEEL
django_admin_enhancer-1.0.0.dist-info/RECORD
django_admin_enhancer-1.0.0.dist-info/metadata.json
django_admin_enhancer-1.0.0.dist-info/DESCRIPTION.rst
django_admin_enhancer-1.0.0.dist-info/LICENSE.txt
django_admin_enhancer-1.0.0.dist-info/top_level.txt
django_admin_enhancer-1.0.0.dist-info/METADATA
